---
title: 解读dis反编译的输出结构
author: Flowerowl
layout: post
permalink: /3397.html
views:
  - 373
duoshuo_thread_id:
  - 1220743779864322604
categories:
  - python
tags:
  - dis
  - python
---
<p class="p1">
  昨晚看了一点python cookbook，对里边的list assignment部分有点疑惑，于是想起用dis看下代码背后的逻辑。
</p>

<p class="p1">
  翻阅了一些资料，梳理一下dis输出的含义。
</p>

<p class="p1">
  <b>关于dis：</b>
</p>

<p class="p2">
  <span class="s1">doc：<a href="http://docs.python.org/2/library/dis.html">http://docs.python.org/2/library/dis.html</a></span>
</p>

<p class="p1">
  <b>关于.pyc</b>
</p>

<p class="p1">
  .pyc文件是.py文件经过编译后的二进制文件，是一种跨平台，由虚拟机执行的字节码（byte code）。
</p>

<p class="p1">
  不通版本的python编译后.pyc的内容是不同的。
</p>

<p class="p2">
  <span class="s1">doc：<a href="http://docs.python.org/2/tutorial/modules.html#compiled-python-files">http://docs.python.org/2/tutorial/modules.html#compiled-python-files</a></span>
</p>

<p class="p1">
  <b>示例代码：</b>
</p>

<p class="p1">
  dis_list_slice.py
</p>

<p class="p1">
  a = [1, 2, 3]
</p>

<p class="p1">
  b = a
</p>

<p class="p1">
  c = a[1:]
</p>

<p class="p1">
  d = [y for x in a]
</p>

<p class="p1">
  a[:] = [x for x in a]
</p>

<p class="p1">
  <b>运行：</b>
</p>

<p class="p1">
   python -m dis dis_list_slice.py
</p>

<p class="p1">
  <b>输出：</b>
</p>

<p class="p1">
  1 0 LOAD_CONST 0 (1)
</p>

<p class="p1">
    3 LOAD_CONST 1 (2)
</p>

<p class="p1">
    6 LOAD_CONST 2 (3)
</p>

<p class="p1">
    9 BUILD_LIST 3
</p>

<p class="p1">
    12 STORE_NAME 0 (a)
</p>

<p class="p1">
  2 15 LOAD_NAME 0 (a)
</p>

<p class="p1">
    18 STORE_NAME 1 (b)
</p>

<p class="p1">
  3 21 LOAD_NAME 0 (a)
</p>

<p class="p1">
    24 LOAD_CONST 0 (1)
</p>

<p class="p1">
    27 SLICE+1
</p>

<p class="p1">
    28 STORE_NAME 2 (c)
</p>

<p class="p1">
  4 31 BUILD_LIST 0
</p>

<p class="p1">
    34 LOAD_NAME 0 (a)
</p>

<p class="p1">
    37 GET_ITER
</p>

<p class="p1">
    >> 38 FOR_ITER 12 (to 53)
</p>

<p class="p1">
    41 STORE_NAME 3 (x)
</p>

<p class="p1">
    44 LOAD_NAME 4 (y)
</p>

<p class="p1">
    47 LIST_APPEND 2
</p>

<p class="p1">
    50 JUMP_ABSOLUTE 38
</p>

<p class="p1">
    >> 53 STORE_NAME 5 (d)
</p>

<p class="p1">
  5 56 BUILD_LIST 0
</p>

<p class="p1">
    59 LOAD_NAME 0 (a)
</p>

<p class="p1">
    62 GET_ITER
</p>

<p class="p1">
    >> 63 FOR_ITER 12 (to 78)
</p>

<p class="p1">
    66 STORE_NAME 3 (x)
</p>

<p class="p1">
    69 LOAD_NAME 3 (x)
</p>

<p class="p1">
    72 LIST_APPEND 2
</p>

<p class="p1">
    75 JUMP_ABSOLUTE 63
</p>

<p class="p1">
    >> 78 LOAD_NAME 0 (a)
</p>

<p class="p1">
    81 STORE_SLICE+0
</p>

<p class="p1">
    82 LOAD_CONST 3 (None)
</p>

<p class="p1">
    85 RETURN_VALUE
</p>

<p class="p1">
  <b>编译：</b>
</p>

<p class="p1">
  我们来看看a = [1,2,3] 的真实 byte code
</p>

<p class="p1">
  >>> co = compile(&#8216;a=[1,2,3]&#8216;, &#8216;<none>&#8217;, &#8216;exec&#8217;)
</p>

<p class="p1">
  >>> co.co_code.encode(&#8216;hex&#8217;)
</p>

<p class="p1">
  ‘6400006401006402006703005a00006500005a010064030053’   (一个十六进制串)
</p>

<p class="p1">
  <b>解读：</b>
</p>

<p class="p1">
  第一行：
</p>

<p class="p1">
  1 0 LOAD_CONST 0 (1)
</p>

<p class="p1">
  第一列1代表源代码第一行语句执行所编译的字节码，也就是执行a = [1, 2, 3]：
</p>

<p class="p1">
    0 LOAD_CONST 0 (1)
</p>

<p class="p1">
    3 LOAD_CONST 1 (2)
</p>

<p class="p1">
    6 LOAD_CONST 2 (3)
</p>

<p class="p1">
    9 BUILD_LIST 3
</p>

<p class="p1">
    12 STORE_NAME 0 (a)
</p>

<p class="p1">
  左边的第一个0代表指令的偏移量（offset），从byte code里边读取 offset = 0 到前两位是64
</p>

<p class="p1">
  操作码（opcode）为LOAD_CONST
</p>

<p class="p1">
  这里的64 和 LOAD_CONST 是一一对应的，
</p>

<p class="p1">
  >>> import opcode
</p>

<p class="p1">
  >>> opcode.opname[0x64]
</p>

<p class="p1">
  &#8216;LOAD_CONST&#8217;
</p>

<p class="p1">
  从这里想到了什么？
</p>

<p class="p1">
  没错我们可以通过修改opcode来加密代码.
</p>

<p class="p1">
  <b>操作指令集合：</b>
</p>

<p class="p2">
  <span class="s2"><a href="http://docs.python.org/2/library/dis.html#python-bytecode-instructions">http://docs.python.org/2/library/dis.html#python-bytecode-instructions</a></span>
</p>

<p class="p1">
  LOAD_CONST 右边的这个0代表oparg，从byte code 里读取就是：0000
</p>

<p class="p1">
  接下来从offset = 3的地方读取两位即：64，opcode为LOAD_CONST，oparg为0100，即为：1
</p>

<p class="p1">
  继续，从offset = 4的地方读取两位即：64，opcode为LOAD_CONST，oparg为0200，即为：2
</p>

<p class="p1">
  这里的oparg是小端序（little-endian）。
</p>

<p class="p1">
  <b>关于大端序以及小端序：</b>
</p>

<p class="p2">
  <span class="s2"><a href="http://zh.wikipedia.org/wiki/%E5%AD%97%E8%8A%82%E5%BA%8F">http://zh.wikipedia.org/wiki/%E5%AD%97%E8%8A%82%E5%BA%8F</a></span>
</p>

<p class="p1">
  注意：oparg的含义取决于opcode
</p>

<p class="p1">
  例如：对于LOAD_NAME以及LOAD_ATTR来说，oparg代表co_names中的下标。
</p>

<p class="p1">
  引用dis.dis 输出源代码第二行的byte code
</p>

<p class="p1">
  2 15 LOAD_NAME 0 (a)
</p>

<p class="p1">
    18 STORE_NAME 1 (b)
</p>

<p class="p1">
  >>> co = compile(&#8216;a=[1,2,3]; b=a&#8217;, &#8216;<none>&#8217;, &#8216;exec&#8217;)
</p>

<p class="p1">
  >>> co.co_names
</p>

<p class="p1">
  (&#8216;a&#8217;, &#8216;b&#8217;)
</p>

<p class="p1">
  >>> co.co_code.encode(‘hex&#8217;)
</p>

<p class="p1">
  &#8217;6400006401006402006703005a00006500005a010064030053&#8242;
</p>

<p class="p1">
  >>> opcode.opname[0x65]
</p>

<p class="p1">
  ‘LOAD_NAME&#8217;
</p>

<p class="p1">
  oparg 为0000，即为0，代表在co_names中下标为0的数据，即为a.
</p>

<p class="p1">
  ====================================================
</p>

<p class="p1">
  如有不对的地方，请指出。
</p>

转载请注明：[于哲的博客][1] &raquo; [解读dis反编译的输出结构][2]

 [1]: http://localhost/wordpress
 [2]: http://localhost/wordpress/3397.html